LICENSE.txt
MANIFEST.in
README.rst
setup.cfg
setup.py
beeng/__init__.py
beeng/engine.py
beeng/finder.py
beeng.egg-info/PKG-INFO
beeng.egg-info/SOURCES.txt
beeng.egg-info/dependency_links.txt
beeng.egg-info/top_level.txt