Metadata-Version: 1.1
Name: beeng
Version: 0.0.1
Summary: A python wrapper for Be10/Be15 calculation engines
Home-page: https://github.com/sbi-aau/beeng-py
Author: Christian Sørensen
Author-email: cgs@sbi.aau.dk
License: BSD
Keywords: be10 be15 beeng development
Platform: UNKNOWN
Classifier: Development Status :: 3 - Alpha
Classifier: Intended Audience :: Developers
Classifier: Topic :: Software Development :: Build Tools
Classifier: License :: OSI Approved :: BSD License
Classifier: Programming Language :: Python :: 2
Classifier: Programming Language :: Python :: 2.7
Classifier: Programming Language :: Python :: 3
Classifier: Programming Language :: Python :: 3.3
Classifier: Programming Language :: Python :: 3.4
Classifier: Programming Language :: Python :: 3.5
